ibkr_event_daemon/__init__.py
ibkr_event_daemon/__main__.py
ibkr_event_daemon/config.py
ibkr_event_daemon/constants.py
ibkr_event_daemon/core.py
ibkr_event_daemon/utils.py
ibkr_event_daemon-0.3.0.dist-info/METADATA
ibkr_event_daemon-0.3.0.dist-info/WHEEL
ibkr_event_daemon-0.3.0.dist-info/entry_points.txt
ibkr_event_daemon-0.3.0.dist-info/RECORD
